observable_jupyter_widget/__init__.py
observable_jupyter_widget/_frontend.py
observable_jupyter_widget/_version.py
observable_jupyter_widget/widget.py
observable_jupyter_widget/labextension/build_log.json
observable_jupyter_widget/labextension/package.json
observable_jupyter_widget/labextension/static/367.265a71be3919bd79d3d7.js
observable_jupyter_widget/labextension/static/367.7dfd1e643bd78201e4e3.js
observable_jupyter_widget/labextension/static/480.598e4ac06e252cf199db.js
observable_jupyter_widget/labextension/static/568.fca37f8be696550a523d.js
observable_jupyter_widget/labextension/static/lib_index_js.4a72c6ca96d6a15e23c7.js
observable_jupyter_widget/labextension/static/lib_index_js.4a72c6ca96d6a15e23c7.js.map
observable_jupyter_widget/labextension/static/lib_plugin_js.e121d5aca5a75473c933.js
observable_jupyter_widget/labextension/static/lib_plugin_js.e121d5aca5a75473c933.js.map
observable_jupyter_widget/labextension/static/lib_widget_js.00ae8ca182e577979c23.js
observable_jupyter_widget/labextension/static/lib_widget_js.00ae8ca182e577979c23.js.map
observable_jupyter_widget/labextension/static/lib_widget_js.03cbdf72da5a052285d6.js
observable_jupyter_widget/labextension/static/lib_widget_js.03cbdf72da5a052285d6.js.map
observable_jupyter_widget/labextension/static/lib_widget_js.068e8b7c599e70b0b4e6.js
observable_jupyter_widget/labextension/static/lib_widget_js.068e8b7c599e70b0b4e6.js.map
observable_jupyter_widget/labextension/static/lib_widget_js.0745efbf1e0daf9c5f02.js
observable_jupyter_widget/labextension/static/lib_widget_js.0745efbf1e0daf9c5f02.js.map
observable_jupyter_widget/labextension/static/lib_widget_js.080657a20e857414a7f7.js
observable_jupyter_widget/labextension/static/lib_widget_js.080657a20e857414a7f7.js.map
observable_jupyter_widget/labextension/static/lib_widget_js.0b234be2a3c8d26015a7.js
observable_jupyter_widget/labextension/static/lib_widget_js.0b234be2a3c8d26015a7.js.map
observable_jupyter_widget-0.1.8.dev0.dist-info/LICENSE.txt
observable_jupyter_widget-0.1.8.dev0.dist-info/METADATA
observable_jupyter_widget-0.1.8.dev0.dist-info/WHEEL
observable_jupyter_widget-0.1.8.dev0.dist-info/top_level.txt
observable_jupyter_widget-0.1.8.dev0.dist-info/RECORD
